{
  "date": "2026-04-29",
  "title": "The Hindu Vocab — 29 April 2026",
  "questions": [
    {
      "id": "hv_20260429_1",
      "q": "**JURISPRUDENCE** means:",
      "options": [
        "The theory, philosophy, and body of law",
        "The act of passing a court judgment",
        "The process of filing a legal complaint",
        "The right to appeal in a higher court"
      ],
      "ans": 0,
      "exp": "JURISPRUDENCE = the theory and study of law. Editorial: 'the jurisprudence on recusal is rich as it takes in precedents and best practices across the globe.'",
      "type": "synonym"
    },
    {
      "id": "hv_20260429_2",
      "q": "**PROCLIVITY** means:",
      "options": [
        "A strong opposition or resistance",
        "A natural tendency or inclination towards something",
        "A formal declaration of intent",
        "A sense of professional responsibility"
      ],
      "ans": 1,
      "exp": "PROCLIVITY = a habitual tendency or inclination. Editorial: 'the judge's alleged ideological proclivity, as reflected in her attendance at events organised by the ABAP.'",
      "type": "synonym"
    },
    {
      "id": "hv_20260429_3",
      "q": "**ADJUDICATION** means:",
      "options": [
        "Voluntary withdrawal from a legal dispute",
        "The filing of supplementary evidence",
        "The formal legal process of resolving a dispute",
        "The appointment of a special legal officer"
      ],
      "ans": 2,
      "exp": "ADJUDICATION = the legal process of arriving at a judgment. Editorial: 'he reasonably apprehended bias in the process of adjudication.'",
      "type": "synonym"
    },
    {
      "id": "hv_20260429_4",
      "q": "**IMPROPRIETY** means:",
      "options": [
        "A lack of legal precedent",
        "An act of judicial courage",
        "Failure to observe standards of honesty or appropriate behaviour",
        "An unsubstantiated allegation"
      ],
      "ans": 2,
      "exp": "IMPROPRIETY = behaviour that is morally wrong or not appropriate. Editorial: 'a judge shall avoid impropriety and the appearance of impropriety in all of the judge's activities.'",
      "type": "synonym"
    },
    {
      "id": "hv_20260429_5",
      "q": "**VITIATE** means:",
      "options": [
        "To strengthen or validate",
        "To impair, corrupt, or render something legally invalid",
        "To formally challenge a judgment",
        "To clarify the terms of a ruling"
      ],
      "ans": 1,
      "exp": "VITIATE = to make something ineffective or invalid. Editorial: 'a mere ground of appearance of bias and not actual bias is enough to vitiate the judgment/order.'",
      "type": "synonym"
    },
    {
      "id": "hv_20260429_6",
      "q": "**ERRONEOUS** means:",
      "options": [
        "Based on established precedent",
        "Containing factual ambiguity",
        "Derived from expert testimony",
        "Wrong; based on error or false information"
      ],
      "ans": 3,
      "exp": "ERRONEOUS = wrong; incorrect. Editorial: 'This is patently erroneous' — referring to the judgment substituting a well-settled legal position with a flawed requirement.",
      "type": "synonym"
    },
    {
      "id": "hv_20260429_7",
      "q": "**RAMIFICATIONS** means:",
      "options": [
        "Detailed legal arguments",
        "Complex consequences or implications of an action",
        "Formal divisions of a statutory body",
        "Procedural delays in court"
      ],
      "ans": 1,
      "exp": "RAMIFICATIONS = the complex or unwelcome consequences of an action. Editorial: 'In a case with serious political ramifications, the grounds raised by Mr. Kejriwal required a more objective assessment.'",
      "type": "synonym"
    },
    {
      "id": "hv_20260429_8",
      "q": "**TANGIBLE** means:",
      "options": [
        "Conditional and reversible",
        "Diplomatically worded",
        "Clear, definite, and perceptible; real",
        "Implied but not stated"
      ],
      "ans": 2,
      "exp": "TANGIBLE = clear and definite; capable of being touched or felt. Editorial (Battle of wills): 'the U.S. should offer tangible concessions to Iran in return for compromises on core issues.'",
      "type": "synonym"
    },
    {
      "id": "hv_20260429_9",
      "q": "**SQUANDERING** means:",
      "options": [
        "Accumulating resources steadily",
        "Wasting something valuable in a reckless or foolish way",
        "Asserting influence over a situation",
        "Negotiating from a position of strength"
      ],
      "ans": 1,
      "exp": "SQUANDERING = wasting something valuable carelessly. Editorial: 'it risks squandering the goodwill it enjoys as the underdog.'",
      "type": "synonym"
    },
    {
      "id": "hv_20260429_10",
      "q": "**PROPHYLACTIC** means:",
      "options": [
        "Curative; designed to treat an existing condition",
        "Intended to prevent disease before it occurs",
        "Relating to post-surgical recovery",
        "Concerned with genetic predisposition"
      ],
      "ans": 1,
      "exp": "PROPHYLACTIC = preventive; intended to prevent disease. Editorial: 'His discovery paved the way for the development of prophylactic vaccines as well as tests to detect the infectious agent.'",
      "type": "synonym"
    },
    {
      "id": "hv_20260429_11",
      "q": "**STIGMATISED** means:",
      "options": [
        "Officially recognised and rewarded",
        "Subjected to peer review",
        "Described or regarded as worthy of disgrace or shame",
        "Carefully documented and archived"
      ],
      "ans": 2,
      "exp": "STIGMATISED = treated as a mark of shame. Editorial (Science article): 'failure is not to be stigmatised but treated as a stepping stone, an essential part of iterative learning.'",
      "type": "synonym"
    },
    {
      "id": "hv_20260429_12",
      "q": "**ITERATIVE** means:",
      "options": [
        "Based on a single definitive experiment",
        "Involving repetition of a process to achieve a result",
        "Derived from statistical modelling",
        "Focused solely on positive outcomes"
      ],
      "ans": 1,
      "exp": "ITERATIVE = relating to a process of repetition. Editorial: 'Science is a messy, iterative, and sometimes uncertain process.'",
      "type": "synonym"
    },
    {
      "id": "hv_20260429_13",
      "q": "**POSTULATES** means:",
      "options": [
        "Disproves through experimentation",
        "Formally publishes in a journal",
        "Suggests or assumes something as a basis for reasoning",
        "Rejects on the basis of prior evidence"
      ],
      "ans": 2,
      "exp": "POSTULATES = suggests or assumes as a fact for further reasoning. Editorial: 'A scientist postulates hypotheses while anticipating that many of them will be discarded.'",
      "type": "synonym"
    },
    {
      "id": "hv_20260429_14",
      "q": "Antonym of **DAUNTING**:",
      "options": [
        "Formidable",
        "Intimidating",
        "Encouraging",
        "Overwhelming"
      ],
      "ans": 2,
      "exp": "DAUNTING = seeming difficult or frightening. Its antonym is ENCOURAGING (inspiring confidence). Editorial: 'headline figures from T.N. and West Bengal appear daunting and unprecedented.'",
      "type": "antonym"
    },
    {
      "id": "hv_20260429_15",
      "q": "Antonym of **OBSTINACY**:",
      "options": [
        "Tenacity",
        "Inflexibility",
        "Compliance",
        "Persistence"
      ],
      "ans": 2,
      "exp": "OBSTINACY = stubbornness; refusal to change. Its antonym is COMPLIANCE (willingness to yield). Editorial: 'the judgment...was an admonition against judicial obstinacy.'",
      "type": "antonym"
    },
    {
      "id": "hv_20260429_16",
      "q": "Antonym of **INSURMOUNTABLE**:",
      "options": [
        "Immense",
        "Surmountable",
        "Pervasive",
        "Intractable"
      ],
      "ans": 1,
      "exp": "INSURMOUNTABLE = too great to be overcome. Its antonym is SURMOUNTABLE (capable of being dealt with). Editorial: 'these gaps are neither inevitable nor insurmountable.'",
      "type": "antonym"
    },
    {
      "id": "hv_20260429_17",
      "q": "Antonym of **INCREMENTAL**:",
      "options": [
        "Gradual",
        "Sequential",
        "Cumulative",
        "Radical"
      ],
      "ans": 3,
      "exp": "INCREMENTAL = increasing by small degrees. Its antonym is RADICAL (drastic, fundamental change). Editorial: 'fear of risk makes researchers more inclined towards safer, incremental projects rather than risky, innovative ideas.'",
      "type": "antonym"
    },
    {
      "id": "hv_20260429_18",
      "q": "Idiom: **'Part and parcel'** means:",
      "options": [
        "A legal document containing multiple clauses",
        "An essential or fundamental element of something",
        "A minor addition to the main argument",
        "A contractual obligation between two parties"
      ],
      "ans": 1,
      "exp": "PART AND PARCEL = an essential or integral element. Editorial: 'Failure is part and parcel of research but many scientists consider discussing it in a scientific forum to be taboo.'",
      "type": "idiom"
    },
    {
      "id": "hv_20260429_19",
      "q": "Idiom: **'A drop in the ocean'** means:",
      "options": [
        "A decisive intervention at a critical moment",
        "An overwhelming crisis with no solution",
        "A tiny, negligible amount compared to what is needed",
        "A gradual effort that eventually produces results"
      ],
      "ans": 2,
      "exp": "A DROP IN THE OCEAN = a very small amount compared to what is needed. Editorial (cervical cancer): 'outreach camps were conducted at regular intervals...but these were merely a drop in the ocean.'",
      "type": "idiom"
    },
    {
      "id": "hv_20260429_20",
      "q": "Phrasal verb: **'Pay off'** (as used in 'experiments do not pay off') means:",
      "options": [
        "To settle a financial debt completely",
        "To produce a successful or profitable result",
        "To dismiss an employee with compensation",
        "To bribe someone to remain silent"
      ],
      "ans": 1,
      "exp": "PAY OFF = to yield a good result; to be successful. Editorial: 'There is always the possibility that experiments do not pay off without a clear explanation.'",
      "type": "phrasal_verb"
    }
  ]
}
